jsonsh/__init__.py
jsonsh/aiojson.py
jsonsh/jsonsh.py
jsonsh-0.1.6.dist-info/LICENSE
jsonsh-0.1.6.dist-info/METADATA
jsonsh-0.1.6.dist-info/WHEEL
jsonsh-0.1.6.dist-info/top_level.txt
jsonsh-0.1.6.dist-info/RECORD
