Metadata-Version: 2.1
Name: jsonsh
Version: 0.1.6
Summary: UNKNOWN
Home-page: https://github.com/Suryansh2002/jsonsh
Author: Suryansh Sharma
License: MIT
Platform: UNKNOWN
Classifier: Programming Language :: Python :: 3
Classifier: License :: OSI Approved :: MIT License
Classifier: Operating System :: OS Independent
Requires-Dist: orjson
Requires-Dist: pydantic
Requires-Dist: ujson
